newrelic_data_exporter/__init__.py
newrelic_data_exporter/newrelic_data_exporter.py
newrelic_data_exporter/queries.yml
newrelic_data_exporter/resources.yml
newrelic_data_exporter-0.0.9.dist-info/LICENSE.txt
newrelic_data_exporter-0.0.9.dist-info/METADATA
newrelic_data_exporter-0.0.9.dist-info/WHEEL
newrelic_data_exporter-0.0.9.dist-info/entry_points.txt
newrelic_data_exporter-0.0.9.dist-info/top_level.txt
newrelic_data_exporter-0.0.9.dist-info/RECORD
