Metadata-Version: 2.1
Name: newrelic-data-exporter
Version: 0.0.9
Summary: A tool to export data from New Relic using GraphQL API
Home-page: https://github.com/atheeque-ahmed/newrelic-data-exporter
Author: Atheeque Ahmed
Author-email: hello@atheeque.com
Classifier: Programming Language :: Python :: 3
Classifier: License :: OSI Approved :: MIT License
Classifier: Operating System :: OS Independent
Requires-Python: >=3.6
License-File: LICENSE.txt
Requires-Dist: requests
Requires-Dist: PyYAML
Requires-Dist: openpyxl
